test/__init__.py
test/base.py
test/test_create_request_header.py
test/test_get_user_detail.py
test/test_get_zalo_quotas.py
test/test_oa_create_request_body.py
zalo_sdk/BaseClient.py
zalo_sdk/ZaloException.py
zalo_sdk/ZaloOAException.py
zalo_sdk/__init__.py
zalo_sdk/oa/Client.py
zalo_sdk/oa/ZaloMessage.py
zalo_sdk/oa/__init__.py
zalo_sdk/zns/Client.py
zalo_sdk/zns/__init__.py
zalo_sdk-0.2.9.dist-info/licenses/LICENSE
zalo_sdk-0.2.9.dist-info/METADATA
zalo_sdk-0.2.9.dist-info/WHEEL
zalo_sdk-0.2.9.dist-info/top_level.txt
zalo_sdk-0.2.9.dist-info/RECORD
