Metadata-Version: 2.4
Name: zalo_sdk
Version: 0.2.9
Summary: Zalo SDK
Home-page: https://github.com/connext-biz/zalo_integration
Author: Khoa Tran
Author-email: khoa@connext.biz
License: MIT License
License-File: LICENSE
Dynamic: author
Dynamic: author-email
Dynamic: description
Dynamic: home-page
Dynamic: license
Dynamic: license-file
Dynamic: summary
